wkmanager/__init__.py
wkmanager/main.py
wkmanager/resources/windows_versions.json
wkmanager-0.1.3.dist-info/METADATA
wkmanager-0.1.3.dist-info/WHEEL
wkmanager-0.1.3.dist-info/RECORD
