Metadata-Version: 2.1
Name: wkmanager
Version: 0.1.3
Summary: Lib to download wkhtmltopdf/wkhtmltoimage (wkhtmltox) based on OS.
License: MIT
Author: Ricardo Castro
Requires-Python: >=3.10,<4.0
Classifier: License :: OSI Approved :: MIT License
Classifier: Programming Language :: Python :: 3
Classifier: Programming Language :: Python :: 3.10
Classifier: Programming Language :: Python :: 3.11
Requires-Dist: lxml (>=4.9.3,<5.0.0)
Requires-Dist: pandas (>=2.0.3,<3.0.0)
Requires-Dist: requests (>=2.31.0,<3.0.0)
